hworder/__init__.py
hworder/generator/__init__.py
hworder/generator/array_generator.py
hworder/sayer/__init__.py
hworder/sayer/echoer.py
hworder-1.0.5.dist-info/LICENSE
hworder-1.0.5.dist-info/METADATA
hworder-1.0.5.dist-info/WHEEL
hworder-1.0.5.dist-info/RECORD
