Metadata-Version: 2.1
Name: hworder
Version: 1.0.5
Summary: A sample Python project
Home-page: https://ya.ru/
License: APACHE
Author: Pavel Mokeev
Author-email: pav3l.mokeev@gmail.com
Requires-Python: >=3.10.0,<4.0.0
Classifier: Intended Audience :: Developers
Classifier: License :: Other/Proprietary License
Classifier: Programming Language :: Python :: 3
Classifier: Programming Language :: Python :: 3.10
Classifier: Programming Language :: Python :: 3.11
Classifier: Programming Language :: Python :: 3.12
Requires-Dist: numpy (>=1.26.4,<2.0.0)
Project-URL: Repository, https://github.com/pmokeev/hello-worlder
